mizu-0.3.0.dist-info/METADATA
mizu-0.3.0.dist-info/WHEEL
mizu-0.3.0.dist-info/license_files/LICENSE
mizu/options.py
mizu/__init__.py
mizu/parse.py
mizu/mizu.pyi
mizu/mizu.cpython-310-darwin.so
mizu-0.3.0.dist-info/RECORD
