Metadata-Version: 2.3
Name: mizu
Version: 0.3.0
Classifier: Programming Language :: Rust
Classifier: Programming Language :: Python :: Implementation :: CPython
Classifier: Programming Language :: Python :: Implementation :: PyPy
License-File: LICENSE
Summary: Markdown library
Requires-Python: >=3.7
Project-URL: Documentation, https://tuna2134.github.io/mizu
Project-URL: Source Code, https://github.com/tuna2134/mizu
